drb_impl_image/__init__.py
drb_impl_image/_version.py
drb_impl_image/cortex.yml
drb_impl_image/execptions.py
drb_impl_image/image_common.py
drb_impl_image/image_list_node.py
drb_impl_image/image_node_factory.py
drb_impl_image-1.0.2.data/data/requirements.txt
drb_impl_image-1.0.2.dist-info/METADATA
drb_impl_image-1.0.2.dist-info/WHEEL
drb_impl_image-1.0.2.dist-info/entry_points.txt
drb_impl_image-1.0.2.dist-info/top_level.txt
drb_impl_image-1.0.2.dist-info/RECORD
