Metadata-Version: 2.1
Name: drb-impl-image
Version: 1.0.2
Summary: DRB Image implementation
Home-page: https://gitlab.com/drb-python/impl/image
Author: GAEL Systems
Author-email: drb-python@gael.fr
License: UNKNOWN
Project-URL: Documentation, https://drb-python.gitlab.io/impl/image
Project-URL: Source, https://gitlab.com/drb-python/impl/image
Platform: UNKNOWN
Classifier: Programming Language :: Python :: 3.8
Classifier: License :: OSI Approved :: Apache Software License
Classifier: Operating System :: OS Independent
Requires-Python: >=3.8
Requires-Dist: drb (<1.1.0,>=1.0.1)
Requires-Dist: drb-impl-file (<1.1.0,>=1.0.1)
Requires-Dist: versioneer (>=0.20)
Requires-Dist: numpy (>=1.21.2)
Requires-Dist: rasterio (>=1.2.8)
Requires-Dist: xarray (>=0.19.0)
